Metadata-Version: 1.0
Name: pyjack
Version: 0.0.2
Summary: A way to hijack python methods and functions and attach callbacks or alter functionality.
Home-page: http://code.google.com/p/pyjack/
Author: Andrew Carter
Author-email: andrewjcarter@gmail.com
License: MIT
Keywords: python function method hijack signal slot signals slots observer publisher subscriber
Platform: UNKNOWN
Classifier: Development Status :: 3 - Alpha
Classifier: Topic :: Utilities
Classifier: License :: OSI Approved :: MIT License
